ex4/binary_counter.v
module binary_counter
   #(parameter N=4)
   (
    input wire clk, reset,
    output wire [N-1:0] binary
   );
 
   reg [N-1:0] r_reg;
   wire [N-1:0] r_next;
 
   always @(posedge clk, negedge reset)
   begin
      if (~reset)
         r_reg <= 0;
      else
         r_reg <= r_next;
	end	
	assign binary  = r_reg;
		assign r_next = r_reg+1;
endmodule

ex4/counter_tb.v
`include "binary_counter.v"
module stimulus;
	// Inputs
	reg clk ;
	reg reset;
	// Output
	wire[3:0] binary;
	// Instantiate the Binary Counter
	binary_counter  #(4) s1  (
		.clk(clk), 
		.reset(reset),
		.binary(binary)
	);
 
 integer i;
 initial 
 begin
 
 clk = 0;
 for(i =0; i<=40; i=i+1)
 begin
  #10 clk = ~clk;
 end
 end
 
initial 
begin

reset =1;
#2 reset = 0;
#2 reset =1;
$monitor("clk=%d binary=%4b",clk,binary);

end
 
 
endmodule

ex4/test.vcd
$date
	Sun Nov 17 18:07:45 2019
$end
$version
	Icarus Verilog
$end
$timescale
	1s
$end
$scope module stimulus $end
$var wire 4 ! binary [3:0] $end
$var reg 1 " clk $end
$var reg 1 # reset $end
$var integer 32 $ i [31:0] $end
$scope module s1 $end
$var wire 4 % binary [3:0] $end
$var wire 1 " clk $end
$var wire 1 # reset $end
$var wire 4 & r_next [3:0] $end
$var reg 4 ' r_reg [3:0] $end
$upscope $end
$upscope $end
$enddefinitions $end
#0
$dumpvars
bx '
bx &
bx %
b0 $
1#
0"
bx !
$end
#2
b1 &
b0 !
b0 %
b0 '
0#
#4
1#
#10
b10 &
b1 !
b1 %
b1 '
b1 $
1"
#20
b10 $
0"
#30
b11 &
b10 !
b10 %
b10 '
b11 $
1"
#40
b100 $
0"
#50
b100 &
b11 !
b11 %
b11 '
b101 $
1"
#60
b110 $
0"
#70
b101 &
b100 !
b100 %
b100 '
b111 $
1"
#80
b1000 $
0"
#90
b110 &
b101 !
b101 %
b101 '
b1001 $
1"
#100
b1010 $
0"
#110
b111 &
b110 !
b110 %
b110 '
b1011 $
1"
#120
b1100 $
0"
#130
b1000 &
b111 !
b111 %
b111 '
b1101 $
1"
#140
b1110 $
0"
#150
b1001 &
b1000 !
b1000 %
b1000 '
b1111 $
1"
#160
b10000 $
0"
#170
b1010 &
b1001 !
b1001 %
b1001 '
b10001 $
1"
#180
b10010 $
0"
#190
b1011 &
b1010 !
b1010 %
b1010 '
b10011 $
1"
#200
b10100 $
0"
#210
b1100 &
b1011 !
b1011 %
b1011 '
b10101 $
1"
#220
b10110 $
0"
#230
b1101 &
b1100 !
b1100 %
b1100 '
b10111 $
1"
#240
b11000 $
0"
#250
b1110 &
b1101 !
b1101 %
b1101 '
b11001 $
1"
#260
b11010 $
0"
#270
b1111 &
b1110 !
b1110 %
b1110 '
b11011 $
1"
#280
b11100 $
0"
#290
b0 &
b1111 !
b1111 %
b1111 '
b11101 $
1"
#300
b11110 $
0"
#310
b1 &
b0 !
b0 %
b0 '
b11111 $
1"
#320
b100000 $
0"
#330
b10 &
b1 !
b1 %
b1 '
b100001 $
1"
#340
b100010 $
0"
#350
b11 &
b10 !
b10 %
b10 '
b100011 $
1"
#360
b100100 $
0"
#370
b100 &
b11 !
b11 %
b11 '
b100101 $
1"
#380
b100110 $
0"
#390
b101 &
b100 !
b100 %
b100 '
b100111 $
1"
#400
b101000 $
0"
#410
b110 &
b101 !
b101 %
b101 '
b101001 $
1"
